yournal/__main__.py
yournal-1.1.2.dist-info/LICENSE
yournal-1.1.2.dist-info/METADATA
yournal-1.1.2.dist-info/WHEEL
yournal-1.1.2.dist-info/entry_points.txt
yournal-1.1.2.dist-info/RECORD
