Metadata-Version: 2.1
Name: yournal
Version: 1.1.2
Summary: Fast (y)ournal script to make daily notes from your terminal.
Home-page: https://github.com/Rikiub/yournal.py
License: MIT
Keywords: journal,daily,notes,script
Author: Rikiub
Author-email: rikiub.dev@gmail.com
Requires-Python: >=3.8,<4.0
Classifier: License :: OSI Approved :: MIT License
Classifier: Programming Language :: Python :: 3
Classifier: Programming Language :: Python :: 3.8
Classifier: Programming Language :: Python :: 3.9
Classifier: Programming Language :: Python :: 3.10
Classifier: Programming Language :: Python :: 3.11
Project-URL: Repository, https://github.com/Rikiub/yournal.py
